streamlit_image_annotation_customize/__init__.py
streamlit_image_annotation_customize/Detection/__init__.py
streamlit_image_annotation_customize/Detection/frontend/build/asset-manifest.json
streamlit_image_annotation_customize/Detection/frontend/build/bootstrap.min.css
streamlit_image_annotation_customize/Detection/frontend/build/index.html
streamlit_image_annotation_customize/Detection/frontend/build/static/js/main.550142da.js
streamlit_image_annotation_customize/Detection/frontend/build/static/js/main.550142da.js.LICENSE.txt
streamlit_image_annotation_customize/Detection/frontend/build/static/js/main.550142da.js.map
streamlit_image_annotation_customize/Detection/frontend/build/static/media/2.64dd1b41a8e665c589dc.png
streamlit_image_annotation_customize-0.4.40.dist-info/LICENSE
streamlit_image_annotation_customize-0.4.40.dist-info/METADATA
streamlit_image_annotation_customize-0.4.40.dist-info/WHEEL
streamlit_image_annotation_customize-0.4.40.dist-info/top_level.txt
streamlit_image_annotation_customize-0.4.40.dist-info/RECORD
