Metadata-Version: 2.1
Name: streamlit_image_annotation_customize
Version: 0.4.40
Summary: streamlit components for image annotation
Home-page: https://github.com/hirune924/Streamlit-Image-Annotation
Author: hirune924
Keywords: Python,Streamlit,React,JavaScript
Requires-Python: >=3.6
License-File: LICENSE
Requires-Dist: streamlit >=0.63
Requires-Dist: matplotlib >=3.7.0
